galapagos_turtle.py
galapagos_turtle-2.3.1.dist-info/METADATA
galapagos_turtle-2.3.1.dist-info/WHEEL
galapagos_turtle-2.3.1.dist-info/entry_points.txt
galapagos_turtle-2.3.1.dist-info/top_level.txt
galapagos_turtle-2.3.1.dist-info/RECORD
