Metadata-Version: 2.4
Name: galapagos_turtle
Version: 2.3.1
Summary: im bored
Author-email: wheatwhole <wheatrefined@gmail.com>
Keywords: galapagos,turtle
Requires-Python: >=3.9
